dataline/__init__.py
dataline/pipeline.py
DataLine-0.1.dist-info/LICENSE
DataLine-0.1.dist-info/METADATA
DataLine-0.1.dist-info/WHEEL
DataLine-0.1.dist-info/top_level.txt
DataLine-0.1.dist-info/RECORD
